slurmize/__init__.py
slurmize/main.py
slurmize-0.0.1.dist-info/entry_points.txt
slurmize-0.0.1.dist-info/COPYING
slurmize-0.0.1.dist-info/WHEEL
slurmize-0.0.1.dist-info/METADATA
slurmize-0.0.1.dist-info/RECORD
